[
  {
    "date": "2023-03-13",
    "strategy": 1.0,
    "benchmark": 1.0
  },
  {
    "date": "2023-03-14",
    "strategy": 1.0,
    "benchmark": 1.0165302478408522
  },
  {
    "date": "2023-03-15",
    "strategy": 1.0,
    "benchmark": 1.010172466546947
  },
  {
    "date": "2023-03-16",
    "strategy": 1.0,
    "benchmark": 1.0278961216652605
  },
  {
    "date": "2023-03-17",
    "strategy": 1.0,
    "benchmark": 1.0158771938930105
  },
  {
    "date": "2023-03-20",
    "strategy": 1.0,
    "benchmark": 1.0256454870240233
  },
  {
    "date": "2023-03-21",
    "strategy": 1.0,
    "benchmark": 1.0391128813676056
  },
  {
    "date": "2023-03-22",
    "strategy": 1.0,
    "benchmark": 1.0213996065693915
  },
  {
    "date": "2023-03-23",
    "strategy": 1.0,
    "benchmark": 1.0241607717158356
  },
  {
    "date": "2023-03-24",
    "strategy": 1.0,
    "benchmark": 1.0308813699122632
  },
  {
    "date": "2023-03-27",
    "strategy": 1.0,
    "benchmark": 1.032808896494533
  },
  {
    "date": "2023-03-28",
    "strategy": 1.0,
    "benchmark": 1.0304907073891567
  },
  {
    "date": "2023-03-29",
    "strategy": 1.0,
    "benchmark": 1.0454686030741895
  },
  {
    "date": "2023-03-30",
    "strategy": 1.0,
    "benchmark": 1.051590438044565
  },
  {
    "date": "2023-03-31",
    "strategy": 1.0,
    "benchmark": 1.066411969860164
  },
  {
    "date": "2023-04-03",
    "strategy": 1.0,
    "benchmark": 1.07047545326162
  },
  {
    "date": "2023-04-04",
    "strategy": 1.0,
    "benchmark": 1.064536427261884
  },
  {
    "date": "2023-04-05",
    "strategy": 1.0,
    "benchmark": 1.06174898178122
  },
  {
    "date": "2023-04-06",
    "strategy": 1.0,
    "benchmark": 1.065890894267872
  },
  {
    "date": "2023-04-10",
    "strategy": 1.0,
    "benchmark": 1.0669847822859673
  },
  {
    "date": "2023-04-11",
    "strategy": 1.0,
    "benchmark": 1.0672715592245867
  },
  {
    "date": "2023-04-12",
    "strategy": 1.0,
    "benchmark": 1.0629213812680038
  },
  {
    "date": "2023-04-13",
    "strategy": 1.0,
    "benchmark": 1.0770397699721066
  },
  {
    "date": "2023-04-14",
    "strategy": 1.0,
    "benchmark": 1.0744088531278624
  },
  {
    "date": "2023-04-17",
    "strategy": 1.0,
    "benchmark": 1.0782639062924018
  },
  {
    "date": "2023-04-18",
    "strategy": 1.0,
    "benchmark": 1.078967543704855
  },
  {
    "date": "2023-04-19",
    "strategy": 1.0,
    "benchmark": 1.0787851466516796
  },
  {
    "date": "2023-04-20",
    "strategy": 1.0,
    "benchmark": 1.0728981046359334
  },
  {
    "date": "2023-04-21",
    "strategy": 1.0,
    "benchmark": 1.0737317432001077
  },
  {
    "date": "2023-04-24",
    "strategy": 1.0,
    "benchmark": 1.0748516644019444
  },
  {
    "date": "2023-04-25",
    "strategy": 1.0,
    "benchmark": 1.057789795881715
  },
  {
    "date": "2023-04-26",
    "strategy": 1.0,
    "benchmark": 1.0533094520064252
  },
  {
    "date": "2023-04-27",
    "strategy": 1.0,
    "benchmark": 1.074278851976141
  },
  {
    "date": "2023-04-28",
    "strategy": 1.0,
    "benchmark": 1.0834478051966518
  },
  {
    "date": "2023-05-01",
    "strategy": 1.0,
    "benchmark": 1.0823538347950636
  },
  {
    "date": "2023-05-02",
    "strategy": 1.0,
    "benchmark": 1.0701889234734792
  },
  {
    "date": "2023-05-03",
    "strategy": 1.0,
    "benchmark": 1.0628434464837655
  },
  {
    "date": "2023-05-04",
    "strategy": 1.0,
    "benchmark": 1.0553152429069048
  },
  {
    "date": "2023-05-05",
    "strategy": 1.0,
    "benchmark": 1.0748516644019444
  },
  {
    "date": "2023-05-08",
    "strategy": 1.0,
    "benchmark": 1.0751381941900855
  },
  {
    "date": "2023-05-09",
    "strategy": 1.0,
    "benchmark": 1.0704234692776302
  },
  {
    "date": "2023-05-10",
    "strategy": 1.0,
    "benchmark": 1.0754248063617193
  },
  {
    "date": "2023-05-11",
    "strategy": 1.0,
    "benchmark": 1.0735492637634394
  },
  {
    "date": "2023-05-12",
    "strategy": 1.0,
    "benchmark": 1.072142648006476
  },
  {
    "date": "2023-05-15",
    "strategy": 1.0,
    "benchmark": 1.0758416668355528
  },
  {
    "date": "2023-05-16",
    "strategy": 1.0,
    "benchmark": 1.068652059414316
  },
  {
    "date": "2023-05-17",
    "strategy": 1.0,
    "benchmark": 1.081624328965855
  },
  {
    "date": "2023-05-18",
    "strategy": 1.0,
    "benchmark": 1.0920438636078664
  },
  {
    "date": "2023-05-19",
    "strategy": 1.0,
    "benchmark": 1.0904550155647132
  },
  {
    "date": "2023-05-22",
    "strategy": 1.0,
    "benchmark": 1.0908978268387954
  },
  {
    "date": "2023-05-23",
    "strategy": 1.0,
    "benchmark": 1.0786547335824939
  },
  {
    "date": "2023-05-24",
    "strategy": 1.0,
    "benchmark": 1.070840164984478
  },
  {
    "date": "2023-05-25",
    "strategy": 1.0,
    "benchmark": 1.0801136628574188
  },
  {
    "date": "2023-05-26",
    "strategy": 1.0,
    "benchmark": 1.0941016384923359
  },
  {
    "date": "2023-05-30",
    "strategy": 1.0,
    "benchmark": 1.0945184165826767
  },
  {
    "date": "2023-05-31",
    "strategy": 1.0,
    "benchmark": 1.0884492246642337
  },
  {
    "date": "2023-06-01",
    "strategy": 1.0,
    "benchmark": 1.0987905773715283
  },
  {
    "date": "2023-06-02",
    "strategy": 1.0,
    "benchmark": 1.1146804583224381
  },
  {
    "date": "2023-06-05",
    "strategy": 1.0,
    "benchmark": 1.1125444191197587
  },
  {
    "date": "2023-06-06",
    "strategy": 1.0,
    "benchmark": 1.1149667409601005
  },
  {
    "date": "2023-06-07",
    "strategy": 1.0,
    "benchmark": 1.1111115230285753
  },
  {
    "date": "2023-06-08",
    "strategy": 1.0,
    "benchmark": 1.1178322859919887
  },
  {
    "date": "2023-06-09",
    "strategy": 1.0,
    "benchmark": 1.1198379945089754
  },
  {
    "date": "2023-06-12",
    "strategy": 1.0,
    "benchmark": 1.1299969501630946
  },
  {
    "date": "2023-06-13",
    "strategy": 1.0,
    "benchmark": 1.1374468894217453
  },
  {
    "date": "2023-06-14",
    "strategy": 1.0,
    "benchmark": 1.138801438811226
  },
  {
    "date": "2023-06-15",
    "strategy": 1.0,
    "benchmark": 1.1529199098988214
  },
  {
    "date": "2023-06-16",
    "strategy": 1.0,
    "benchmark": 1.148992935945022
  },
  {
    "date": "2023-06-20",
    "strategy": 1.0,
    "benchmark": 1.1430318311692014
  },
  {
    "date": "2023-06-21",
    "strategy": 1.0,
    "benchmark": 1.1371751886623178
  },
  {
    "date": "2023-06-22",
    "strategy": 1.0,
    "benchmark": 1.141280028577186
  },
  {
    "date": "2023-06-23",
    "strategy": 1.0,
    "benchmark": 1.1326519229872518
  },
  {
    "date": "2023-06-26",
    "strategy": 1.0,
    "benchmark": 1.128024112659756
  },
  {
    "date": "2023-06-27",
    "strategy": 1.0,
    "benchmark": 1.1403910283058147
  },
  {
    "date": "2023-06-28",
    "strategy": 1.0,
    "benchmark": 1.1409663122364038
  },
  {
    "date": "2023-06-29",
    "strategy": 1.0,
    "benchmark": 1.145463215193757
  },
  {
    "date": "2023-06-30",
    "strategy": 1.0,
    "benchmark": 1.158980451550515
  },
  {
    "date": "2023-07-03",
    "strategy": 1.0054481744477497,
    "benchmark": 1.1603139107658254
  },
  {
    "date": "2023-07-05",
    "strategy": 1.0064868354769454,
    "benchmark": 1.1585882237410443
  },
  {
    "date": "2023-07-06",
    "strategy": 0.9878589976001947,
    "benchmark": 1.1495159063576494
  },
  {
    "date": "2023-07-07",
    "strategy": 0.994783193773024,
    "benchmark": 1.1466137006714419
  },
  {
    "date": "2023-07-10",
    "strategy": 1.011291752515351,
    "benchmark": 1.1495159063576494
  },
  {
    "date": "2023-07-11",
    "strategy": 1.0133177410809615,
    "benchmark": 1.156836421149029
  },
  {
    "date": "2023-07-12",
    "strategy": 1.0136911750437378,
    "benchmark": 1.166144355321982
  },
  {
    "date": "2023-07-13",
    "strategy": 1.0162537110683507,
    "benchmark": 1.1753998112099877
  },
  {
    "date": "2023-07-14",
    "strategy": 1.0079562814666732,
    "benchmark": 1.1746678338759935
  },
  {
    "date": "2023-07-17",
    "strategy": 1.0083105850061809,
    "benchmark": 1.1787463934566416
  },
  {
    "date": "2023-07-18",
    "strategy": 1.0203730263956583,
    "benchmark": 1.1875052416497327
  },
  {
    "date": "2023-07-19",
    "strategy": 1.022372672711482,
    "benchmark": 1.1901460445131193
  },
  {
    "date": "2023-07-20",
    "strategy": 1.0023215365670415,
    "benchmark": 1.1822500810241652
  },
  {
    "date": "2023-07-21",
    "strategy": 1.0028061479233283,
    "benchmark": 1.1822500810241652
  },
  {
    "date": "2023-07-24",
    "strategy": 1.0045704644375737,
    "benchmark": 1.187531357216967
  },
  {
    "date": "2023-07-25",
    "strategy": 1.003348375720004,
    "benchmark": 1.1907735595781768
  },
  {
    "date": "2023-07-26",
    "strategy": 1.0064620570549274,
    "benchmark": 1.190956615699295
  },
  {
    "date": "2023-07-27",
    "strategy": 1.0244447777082235,
    "benchmark": 1.1830604874433552
  },
  {
    "date": "2023-07-28",
    "strategy": 1.0291294988733453,
    "benchmark": 1.1946430298539654
  },
  {
    "date": "2023-07-31",
    "strategy": 1.037219417227708,
    "benchmark": 1.1969178852421012
  },
  {
    "date": "2023-08-01",
    "strategy": 1.0379375594634588,
    "benchmark": 1.193492709143266
  },
  {
    "date": "2023-08-02",
    "strategy": 1.0114498638244742,
    "benchmark": 1.1768902109791821
  },
  {
    "date": "2023-08-03",
    "strategy": 1.0031741484201666,
    "benchmark": 1.1735174307818013
  },
  {
    "date": "2023-08-04",
    "strategy": 1.003124948395682,
    "benchmark": 1.1682098742547795
  },
  {
    "date": "2023-08-07",
    "strategy": 1.0101899623929818,
    "benchmark": 1.178406643932118
  },
  {
    "date": "2023-08-08",
    "strategy": 0.9785194199852005,
    "benchmark": 1.1732821435262144
  },
  {
    "date": "2023-08-09",
    "strategy": 0.9400755356456946,
    "benchmark": 1.1654385759387147
  },
  {
    "date": "2023-08-10",
    "strategy": 0.9716052741438732,
    "benchmark": 1.1658569193154196
  },
  {
    "date": "2023-08-11",
    "strategy": 0.9635533865353708,
    "benchmark": 1.165177008348908
  },
  {
    "date": "2023-08-14",
    "strategy": 0.9775512509799138,
    "benchmark": 1.1716088524028876
  },
  {
    "date": "2023-08-15",
    "strategy": 0.9655342782943578,
    "benchmark": 1.1579608734429725
  },
  {
    "date": "2023-08-16",
    "strategy": 0.956774268000928,
    "benchmark": 1.149463675223181
  },
  {
    "date": "2023-08-17",
    "strategy": 0.9387781784361459,
    "benchmark": 1.1407049094135828
  },
  {
    "date": "2023-08-18",
    "strategy": 0.9410754045982526,
    "benchmark": 1.1412539130099517
  },
  {
    "date": "2023-08-21",
    "strategy": 0.9469797865359877,
    "benchmark": 1.1486792196042397
  },
  {
    "date": "2023-08-22",
    "strategy": 0.9518316167947573,
    "benchmark": 1.1455677598461866
  },
  {
    "date": "2023-08-23",
    "strategy": 0.9735316777390661,
    "benchmark": 1.1583269033017163
  },
  {
    "date": "2023-08-24",
    "strategy": 0.9435110976529365,
    "benchmark": 1.142273491117494
  },
  {
    "date": "2023-08-25",
    "strategy": 0.9534282765602987,
    "benchmark": 1.1503263127768395
  },
  {
    "date": "2023-08-28",
    "strategy": 0.9631843212032979,
    "benchmark": 1.1576209591514632
  },
  {
    "date": "2023-08-29",
    "strategy": 0.9903333094800256,
    "benchmark": 1.174354117535211
  },
  {
    "date": "2023-08-30",
    "strategy": 1.0043427601936499,
    "benchmark": 1.1791911819345522
  },
  {
    "date": "2023-08-31",
    "strategy": 1.0094272140610216,
    "benchmark": 1.1774654949097711
  },
  {
    "date": "2023-09-01",
    "strategy": 1.0330559460665412,
    "benchmark": 1.17966159167874
  },
  {
    "date": "2023-09-05",
    "strategy": 1.0268469411287375,
    "benchmark": 1.1745632068400707
  },
  {
    "date": "2023-09-06",
    "strategy": 1.0286532146620724,
    "benchmark": 1.1666672433511167
  },
  {
    "date": "2023-09-07",
    "strategy": 1.0319627331587509,
    "benchmark": 1.163085373848876
  },
  {
    "date": "2023-09-08",
    "strategy": 1.0408593512760684,
    "benchmark": 1.1648370116739057
  },
  {
    "date": "2023-09-11",
    "strategy": 1.0255878894009947,
    "benchmark": 1.1724979350577516
  },
  {
    "date": "2023-09-12",
    "strategy": 1.038148103885004,
    "benchmark": 1.1660659262367863
  },
  {
    "date": "2023-09-13",
    "strategy": 1.0222173787713225,
    "benchmark": 1.1674255834028238
  },
  {
    "date": "2023-09-14",
    "strategy": 1.0327207133351215,
    "benchmark": 1.1774916104770055
  },
  {
    "date": "2023-09-15",
    "strategy": 1.0181105915695088,
    "benchmark": 1.1633046787068493
  },
  {
    "date": "2023-09-18",
    "strategy": 1.0285989524491268,
    "benchmark": 1.1639869787946537
  },
  {
    "date": "2023-09-19",
    "strategy": 1.0185663852617954,
    "benchmark": 1.1615731424540758
  },
  {
    "date": "2023-09-20",
    "strategy": 1.012688384452798,
    "benchmark": 1.1508942645765645
  },
  {
    "date": "2023-09-21",
    "strategy": 1.000024513041694,
    "benchmark": 1.1318719160769244
  },
  {
    "date": "2023-09-22",
    "strategy": 1.0008978253716345,
    "benchmark": 1.1293267604487396
  },
  {
    "date": "2023-09-25",
    "strategy": 1.0138736109368782,
    "benchmark": 1.134075921661207
  },
  {
    "date": "2023-09-26",
    "strategy": 1.0049336745951243,
    "benchmark": 1.117414931217198
  },
  {
    "date": "2023-09-27",
    "strategy": 1.0242823356634132,
    "benchmark": 1.1178608730640085
  },
  {
    "date": "2023-09-28",
    "strategy": 1.0315638557224145,
    "benchmark": 1.1243417352962355
  },
  {
    "date": "2023-09-29",
    "strategy": 1.0083949499148603,
    "benchmark": 1.1216128644789896
  },
  {
    "date": "2023-10-02",
    "strategy": 1.0065279936895637,
    "benchmark": 1.121166840248686
  },
  {
    "date": "2023-10-03",
    "strategy": 0.991287033584022,
    "benchmark": 1.1061588745887623
  },
  {
    "date": "2023-10-04",
    "strategy": 0.994065607961736,
    "benchmark": 1.1142138382189215
  },
  {
    "date": "2023-10-05",
    "strategy": 0.9941897140854318,
    "benchmark": 1.113794176706331
  },
  {
    "date": "2023-10-06",
    "strategy": 1.0056408088130273,
    "benchmark": 1.1270181278285343
  },
  {
    "date": "2023-10-09",
    "strategy": 1.0214876842745635,
    "benchmark": 1.1342332741325554
  },
  {
    "date": "2023-10-10",
    "strategy": 1.0315102975632615,
    "benchmark": 1.140136792846872
  },
  {
    "date": "2023-10-11",
    "strategy": 1.0422815206488796,
    "benchmark": 1.1448071954401726
  },
  {
    "date": "2023-10-12",
    "strategy": 1.0364726879713801,
    "benchmark": 1.1378279130761881
  },
  {
    "date": "2023-10-13",
    "strategy": 1.0340165883066286,
    "benchmark": 1.1321604230688938
  },
  {
    "date": "2023-10-16",
    "strategy": 1.0431907387277388,
    "benchmark": 1.144072499450914
  },
  {
    "date": "2023-10-17",
    "strategy": 1.0525069571253858,
    "benchmark": 1.144020021165967
  },
  {
    "date": "2023-10-18",
    "strategy": 1.0454520694136193,
    "benchmark": 1.128775779648542
  },
  {
    "date": "2023-10-19",
    "strategy": 1.0329717156344662,
    "benchmark": 1.1188579604780022
  },
  {
    "date": "2023-10-20",
    "strategy": 1.0076284571993293,
    "benchmark": 1.1051093912733143
  },
  {
    "date": "2023-10-23",
    "strategy": 1.0043625316626195,
    "benchmark": 1.103193975064494
  },
  {
    "date": "2023-10-24",
    "strategy": 1.0069965618835643,
    "benchmark": 1.1115114948863742
  },
  {
    "date": "2023-10-25",
    "strategy": 1.0002283829099843,
    "benchmark": 1.0955588377139107
  },
  {
    "date": "2023-10-26",
    "strategy": 0.9867280123637332,
    "benchmark": 1.0824399255450945
  },
  {
    "date": "2023-10-27",
    "strategy": 0.9797567585470005,
    "benchmark": 1.0775335766282643
  },
  {
    "date": "2023-10-30",
    "strategy": 0.9857614452769478,
    "benchmark": 1.0904162129395798
  },
  {
    "date": "2023-10-31",
    "strategy": 0.993864356722445,
    "benchmark": 1.097264340782943
  },
  {
    "date": "2023-11-01",
    "strategy": 1.0155801357882157,
    "benchmark": 1.1089662568746965
  },
  {
    "date": "2023-11-02",
    "strategy": 1.033418262165205,
    "benchmark": 1.1302189736763322
  },
  {
    "date": "2023-11-03",
    "strategy": 1.0337480096379417,
    "benchmark": 1.1405303387922283
  },
  {
    "date": "2023-11-06",
    "strategy": 1.040154360814639,
    "benchmark": 1.1431541706560873
  },
  {
    "date": "2023-11-07",
    "strategy": 1.0255642356510495,
    "benchmark": 1.146407659555818
  },
  {
    "date": "2023-11-08",
    "strategy": 1.0232104959912527,
    "benchmark": 1.1472472297314775
  },
  {
    "date": "2023-11-09",
    "strategy": 1.016532404206514,
    "benchmark": 1.1383001352572186
  },
  {
    "date": "2023-11-10",
    "strategy": 1.0266329179006468,
    "benchmark": 1.1560630049181297
  },
  {
    "date": "2023-11-13",
    "strategy": 1.0343621601718156,
    "benchmark": 1.1549611257012278
  },
  {
    "date": "2023-11-14",
    "strategy": 1.0566285249518161,
    "benchmark": 1.1773683647716982
  },
  {
    "date": "2023-11-15",
    "strategy": 1.0515109255997062,
    "benchmark": 1.1798608773479502
  },
  {
    "date": "2023-11-16",
    "strategy": 1.0415809712815272,
    "benchmark": 1.1813039889922472
  },
  {
    "date": "2023-11-17",
    "strategy": 1.0529589539450244,
    "benchmark": 1.1827732162037785
  },
  {
    "date": "2023-11-20",
    "strategy": 1.0528451759092465,
    "benchmark": 1.1918777455328786
  },
  {
    "date": "2023-11-21",
    "strategy": 1.044488188927727,
    "benchmark": 1.189280111619747
  },
  {
    "date": "2023-11-22",
    "strategy": 1.052541577446694,
    "benchmark": 1.1938718379773732
  },
  {
    "date": "2023-11-24",
    "strategy": 1.0550336881384168,
    "benchmark": 1.194606451583139
  },
  {
    "date": "2023-11-27",
    "strategy": 1.0611862851100384,
    "benchmark": 1.192455006667296
  },
  {
    "date": "2023-11-28",
    "strategy": 1.0576954452038119,
    "benchmark": 1.1936356445033651
  },
  {
    "date": "2023-11-29",
    "strategy": 1.0619713990600237,
    "benchmark": 1.1927959919442126
  },
  {
    "date": "2023-11-30",
    "strategy": 1.072394263933446,
    "benchmark": 1.1974925101047473
  },
  {
    "date": "2023-12-01",
    "strategy": 1.0930591422054048,
    "benchmark": 1.2045769961891044
  },
  {
    "date": "2023-12-04",
    "strategy": 1.0959296887108836,
    "benchmark": 1.1982534864282257
  },
  {
    "date": "2023-12-05",
    "strategy": 1.092402120751569,
    "benchmark": 1.1980172929542177
  },
  {
    "date": "2023-12-06",
    "strategy": 1.0866438012404898,
    "benchmark": 1.1931896202730616
  },
  {
    "date": "2023-12-07",
    "strategy": 1.0963776807656984,
    "benchmark": 1.202294149602162
  },
  {
    "date": "2023-12-08",
    "strategy": 1.1170200234431762,
    "benchmark": 1.2074630547107128
  },
  {
    "date": "2023-12-11",
    "strategy": 1.1215089668300584,
    "benchmark": 1.2121594904877548
  },
  {
    "date": "2023-12-12",
    "strategy": 1.1285783036986732,
    "benchmark": 1.217695661207442
  },
  {
    "date": "2023-12-13",
    "strategy": 1.145251475794721,
    "benchmark": 1.2344878885555652
  },
  {
    "date": "2023-12-14",
    "strategy": 1.1394797907558016,
    "benchmark": 1.2384498754938273
  },
  {
    "date": "2023-12-15",
    "strategy": 1.1398746864591658,
    "benchmark": 1.2364107192787424
  },
  {
    "date": "2023-12-18",
    "strategy": 1.1472430498556723,
    "benchmark": 1.2433656161288424
  },
  {
    "date": "2023-12-19",
    "strategy": 1.156344691896871,
    "benchmark": 1.2509264435688727
  },
  {
    "date": "2023-12-20",
    "strategy": 1.1378335813175962,
    "benchmark": 1.2335920504542872
  },
  {
    "date": "2023-12-21",
    "strategy": 1.1506585173208361,
    "benchmark": 1.245288776385991
  },
  {
    "date": "2023-12-22",
    "strategy": 1.153063133562466,
    "benchmark": 1.247791422131864
  },
  {
    "date": "2023-12-26",
    "strategy": 1.1562865832582319,
    "benchmark": 1.253060176033752
  },
  {
    "date": "2023-12-27",
    "strategy": 1.1687016364685254,
    "benchmark": 1.2553258868541814
  },
  {
    "date": "2023-12-28",
    "strategy": 1.1692722745806434,
    "benchmark": 1.2558000038555475
  },
  {
    "date": "2023-12-29",
    "strategy": 1.155691353538527,
    "benchmark": 1.25216450269946
  },
  {
    "date": "2024-01-02",
    "strategy": 1.1626497300448466,
    "benchmark": 1.245156962797427
  },
  {
    "date": "2024-01-03",
    "strategy": 1.1313933113426136,
    "benchmark": 1.2349881211241656
  },
  {
    "date": "2024-01-04",
    "strategy": 1.134884226178937,
    "benchmark": 1.2310099870213045
  },
  {
    "date": "2024-01-05",
    "strategy": 1.1536872851671653,
    "benchmark": 1.232696294736502
  },
  {
    "date": "2024-01-08",
    "strategy": 1.1647302104473976,
    "benchmark": 1.250294067877737
  },
  {
    "date": "2024-01-09",
    "strategy": 1.1533622644560635,
    "benchmark": 1.248397435105287
  },
  {
    "date": "2024-01-10",
    "strategy": 1.150780104913118,
    "benchmark": 1.2554575356757596
  },
  {
    "date": "2024-01-11",
    "strategy": 1.1306829475708349,
    "benchmark": 1.254904412904748
  },
  {
    "date": "2024-01-12",
    "strategy": 1.1204770183484818,
    "benchmark": 1.2557736411378346
  },
  {
    "date": "2024-01-16",
    "strategy": 1.1109296875117076,
    "benchmark": 1.2511634608778093
  },
  {
    "date": "2024-01-17",
    "strategy": 1.1005372206963597,
    "benchmark": 1.244208646411202
  },
  {
    "date": "2024-01-18",
    "strategy": 1.082761668303349,
    "benchmark": 1.2552731614187558
  },
  {
    "date": "2024-01-19",
    "strategy": 1.1092595944133739,
    "benchmark": 1.2709214939686222
  },
  {
    "date": "2024-01-22",
    "strategy": 1.1191510419340822,
    "benchmark": 1.2736086787384846
  },
  {
    "date": "2024-01-23",
    "strategy": 1.1189533870500274,
    "benchmark": 1.2773231856642178
  },
  {
    "date": "2024-01-24",
    "strategy": 1.1232826544241343,
    "benchmark": 1.2787195858680676
  },
  {
    "date": "2024-01-25",
    "strategy": 1.1320933141713032,
    "benchmark": 1.2856744003346747
  },
  {
    "date": "2024-01-26",
    "strategy": 1.1398523700976009,
    "benchmark": 1.2840409828218884
  },
  {
    "date": "2024-01-29",
    "strategy": 1.1520252144458347,
    "benchmark": 1.2942099068786428
  },
  {
    "date": "2024-01-30",
    "strategy": 1.1474399277126668,
    "benchmark": 1.2932088650569922
  },
  {
    "date": "2024-01-31",
    "strategy": 1.1178149283909373,
    "benchmark": 1.2721069924307695
  },
  {
    "date": "2024-02-01",
    "strategy": 1.1366633173656566,
    "benchmark": 1.2887565315692722
  },
  {
    "date": "2024-02-02",
    "strategy": 1.1517527782939754,
    "benchmark": 1.3023239394731774
  },
  {
    "date": "2024-02-05",
    "strategy": 1.1595090031879047,
    "benchmark": 1.297581945624588
  },
  {
    "date": "2024-02-06",
    "strategy": 1.1583339428734674,
    "benchmark": 1.3013492603692396
  },
  {
    "date": "2024-02-07",
    "strategy": 1.182424437967363,
    "benchmark": 1.3122028736350908
  },
  {
    "date": "2024-02-08",
    "strategy": 1.1935943124061006,
    "benchmark": 1.3127824415073082
  },
  {
    "date": "2024-02-09",
    "strategy": 1.2133945490390121,
    "benchmark": 1.320369631665051
  },
  {
    "date": "2024-02-12",
    "strategy": 1.2012662893643453,
    "benchmark": 1.319790063792834
  },
  {
    "date": "2024-02-13",
    "strategy": 1.1945174608537825,
    "benchmark": 1.301612558012396
  },
  {
    "date": "2024-02-14",
    "strategy": 1.2089739443128695,
    "benchmark": 1.3134410151491709
  },
  {
    "date": "2024-02-15",
    "strategy": 1.2124632764015446,
    "benchmark": 1.3225034465134236
  },
  {
    "date": "2024-02-16",
    "strategy": 1.1973630937488666,
    "benchmark": 1.315917380560824
  },
  {
    "date": "2024-02-20",
    "strategy": 1.1779510896664147,
    "benchmark": 1.3086728233498546
  },
  {
    "date": "2024-02-21",
    "strategy": 1.1305224829263398,
    "benchmark": 1.309858239428509
  },
  {
    "date": "2024-02-22",
    "strategy": 1.1930422960785054,
    "benchmark": 1.3369664453681283
  },
  {
    "date": "2024-02-23",
    "strategy": 1.1999868940009877,
    "benchmark": 1.3378884814201333
  },
  {
    "date": "2024-02-26",
    "strategy": 1.2124306453119664,
    "benchmark": 1.3329884760322528
  },
  {
    "date": "2024-02-27",
    "strategy": 1.2084116822057833,
    "benchmark": 1.335464759060413
  },
  {
    "date": "2024-02-28",
    "strategy": 1.2063482234859522,
    "benchmark": 1.3336997751095412
  },
  {
    "date": "2024-02-29",
    "strategy": 1.2211232279519937,
    "benchmark": 1.3384944943935562
  },
  {
    "date": "2024-03-01",
    "strategy": 1.2786900162496169,
    "benchmark": 1.3510605309418393
  },
  {
    "date": "2024-03-04",
    "strategy": 1.2911958887325166,
    "benchmark": 1.3496115700695497
  },
  {
    "date": "2024-03-05",
    "strategy": 1.2578590419558568,
    "benchmark": 1.3361234150857686
  },
  {
    "date": "2024-03-06",
    "strategy": 1.2776283507906336,
    "benchmark": 1.342893855295372
  },
  {
    "date": "2024-03-07",
    "strategy": 1.3128981059782825,
    "benchmark": 1.3562239163563692
  },
  {
    "date": "2024-03-08",
    "strategy": 1.2948570039921345,
    "benchmark": 1.3480836858111076
  },
  {
    "date": "2024-03-11",
    "strategy": 1.27244686919757,
    "benchmark": 1.3469245500666729
  },
  {
    "date": "2024-03-12",
    "strategy": 1.2881940658573112,
    "benchmark": 1.3614139940225833
  },
  {
    "date": "2024-03-13",
    "strategy": 1.2822473108326784,
    "benchmark": 1.3592799320237323
  },
  {
    "date": "2024-03-14",
    "strategy": 1.2598250971278715,
    "benchmark": 1.3565928296373626
  },
  {
    "date": "2024-03-15",
    "strategy": 1.254584530820697,
    "benchmark": 1.3472778104840244
  },
  {
    "date": "2024-03-18",
    "strategy": 1.2634926338740204,
    "benchmark": 1.3552847445378509
  },
  {
    "date": "2024-03-19",
    "strategy": 1.259601329804589,
    "benchmark": 1.3628162434544255
  },
  {
    "date": "2024-03-20",
    "strategy": 1.281062983868564,
    "benchmark": 1.3754213297783209
  },
  {
    "date": "2024-03-21",
    "strategy": 1.3066870883130313,
    "benchmark": 1.379966838996457
  },
  {
    "date": "2024-03-22",
    "strategy": 1.3045645716475014,
    "benchmark": 1.3773505040304477
  },
  {
    "date": "2024-03-25",
    "strategy": 1.3050095820085128,
    "benchmark": 1.373545210495591
  },
  {
    "date": "2024-03-26",
    "strategy": 1.2990300898526004,
    "benchmark": 1.3710081284497058
  },
  {
    "date": "2024-03-27",
    "strategy": 1.30349958050618,
    "benchmark": 1.382529789459098
  },
  {
    "date": "2024-03-28",
    "strategy": 1.2960719401726206,
    "benchmark": 1.3822656679810128
  },
  {
    "date": "2024-04-01",
    "strategy": 1.3134092554604384,
    "benchmark": 1.379860811441156
  },
  {
    "date": "2024-04-02",
    "strategy": 1.303579101313278,
    "benchmark": 1.3710877109038013
  },
  {
    "date": "2024-04-03",
    "strategy": 1.3353553187387428,
    "benchmark": 1.372593598769652
  },
  {
    "date": "2024-04-04",
    "strategy": 1.3118658964081258,
    "benchmark": 1.355839762129198
  },
  {
    "date": "2024-04-05",
    "strategy": 1.339657687508594,
    "benchmark": 1.3700038736718338
  },
  {
    "date": "2024-04-08",
    "strategy": 1.3322055906975503,
    "benchmark": 1.3707702873058407
  },
  {
    "date": "2024-04-09",
    "strategy": 1.3122633330995266,
    "benchmark": 1.3723560871597582
  },
  {
    "date": "2024-04-10",
    "strategy": 1.3057024545234641,
    "benchmark": 1.358614355784977
  },
  {
    "date": "2024-04-11",
    "strategy": 1.3324248797157268,
    "benchmark": 1.368867887688891
  },
  {
    "date": "2024-04-12",
    "strategy": 1.295736348666498,
    "benchmark": 1.3499731512196793
  },
  {
    "date": "2024-04-15",
    "strategy": 1.270849921649008,
    "benchmark": 1.3330605615884987
  },
  {
    "date": "2024-04-16",
    "strategy": 1.284296235248029,
    "benchmark": 1.330629342330929
  },
  {
    "date": "2024-04-17",
    "strategy": 1.258389857854756,
    "benchmark": 1.322754386632652
  },
  {
    "date": "2024-04-18",
    "strategy": 1.2442273460786533,
    "benchmark": 1.3200324360288058
  },
  {
    "date": "2024-04-19",
    "strategy": 1.1965156444428435,
    "benchmark": 1.3085108574029065
  },
  {
    "date": "2024-04-22",
    "strategy": 1.2094376068187456,
    "benchmark": 1.3205610085189474
  },
  {
    "date": "2024-04-23",
    "strategy": 1.2462007394716417,
    "benchmark": 1.3362316669953769
  },
  {
    "date": "2024-04-24",
    "strategy": 1.2378736096752632,
    "benchmark": 1.3355973141004127
  },
  {
    "date": "2024-04-25",
    "strategy": 1.2594749537777568,
    "benchmark": 1.3305235619261062
  },
  {
    "date": "2024-04-26",
    "strategy": 1.2965275600354276,
    "benchmark": 1.3431288130169874
  },
  {
    "date": "2024-04-29",
    "strategy": 1.3056220760656747,
    "benchmark": 1.3478855535107972
  },
  {
    "date": "2024-04-30",
    "strategy": 1.2879354519304858,
    "benchmark": 1.326533235066303
  },
  {
    "date": "2024-05-01",
    "strategy": 1.2887359811760497,
    "benchmark": 1.3222258965260034
  },
  {
    "date": "2024-05-02",
    "strategy": 1.3144055716717327,
    "benchmark": 1.3345932240895264
  },
  {
    "date": "2024-05-03",
    "strategy": 1.3202673836025793,
    "benchmark": 1.3511359942212924
  },
  {
    "date": "2024-05-06",
    "strategy": 1.3453715956078112,
    "benchmark": 1.3650887097212687
  },
  {
    "date": "2024-05-07",
    "strategy": 1.3388928936079212,
    "benchmark": 1.3665950918880765
  },
  {
    "date": "2024-05-08",
    "strategy": 1.3623037671861873,
    "benchmark": 1.366727070243626
  },
  {
    "date": "2024-05-09",
    "strategy": 1.3928492369586425,
    "benchmark": 1.37460194355841
  },
  {
    "date": "2024-05-10",
    "strategy": 1.3920512381058503,
    "benchmark": 1.3763728591207671
  },
  {
    "date": "2024-05-13",
    "strategy": 1.3727472627249555,
    "benchmark": 1.3765576452952353
  },
  {
    "date": "2024-05-14",
    "strategy": 1.3813266394892305,
    "benchmark": 1.3828734933912785
  },
  {
    "date": "2024-05-15",
    "strategy": 1.4060040975911257,
    "benchmark": 1.3999977262155974
  },
  {
    "date": "2024-05-16",
    "strategy": 1.3774245951911508,
    "benchmark": 1.3971172697715029
  },
  {
    "date": "2024-05-17",
    "strategy": 1.3834015162340016,
    "benchmark": 1.3991256145602609
  },
  {
    "date": "2024-05-20",
    "strategy": 1.3890894876946331,
    "benchmark": 1.4007376947483983
  },
  {
    "date": "2024-05-21",
    "strategy": 1.4047191476294416,
    "benchmark": 1.4041729216333614
  },
  {
    "date": "2024-05-22",
    "strategy": 1.4008208497162706,
    "benchmark": 1.4001298693381328
  },
  {
    "date": "2024-05-23",
    "strategy": 1.391973858961102,
    "benchmark": 1.3899029473024103
  },
  {
    "date": "2024-05-24",
    "strategy": 1.4211052331766127,
    "benchmark": 1.3990990870755624
  },
  {
    "date": "2024-05-28",
    "strategy": 1.4024992440075097,
    "benchmark": 1.4000768143687357
  },
  {
    "date": "2024-05-29",
    "strategy": 1.380762828211142,
    "benchmark": 1.3902730139523036
  },
  {
    "date": "2024-05-30",
    "strategy": 1.3891680860466218,
    "benchmark": 1.3810500995439745
  },
  {
    "date": "2024-05-31",
    "strategy": 1.3785727674283812,
    "benchmark": 1.3936289879171426
  },
  {
    "date": "2024-06-03",
    "strategy": 1.3712830191593919,
    "benchmark": 1.394765221050564
  },
  {
    "date": "2024-06-04",
    "strategy": 1.3567821721325524,
    "benchmark": 1.3963242462693046
  },
  {
    "date": "2024-06-05",
    "strategy": 1.389737870811192,
    "benchmark": 1.4129199066034819
  },
  {
    "date": "2024-06-06",
    "strategy": 1.3735680565934418,
    "benchmark": 1.412893543885769
  },
  {
    "date": "2024-06-07",
    "strategy": 1.3689314808808228,
    "benchmark": 1.4111760128267803
  },
  {
    "date": "2024-06-10",
    "strategy": 1.3931944847401483,
    "benchmark": 1.4155360768025056
  },
  {
    "date": "2024-06-11",
    "strategy": 1.3951344993677082,
    "benchmark": 1.4189451057367415
  },
  {
    "date": "2024-06-12",
    "strategy": 1.392954738195078,
    "benchmark": 1.4305987451016835
  },
  {
    "date": "2024-06-13",
    "strategy": 1.3861198212564814,
    "benchmark": 1.4334793663127636
  },
  {
    "date": "2024-06-14",
    "strategy": 1.3757794654525133,
    "benchmark": 1.4343516427350858
  },
  {
    "date": "2024-06-17",
    "strategy": 1.3810733645327775,
    "benchmark": 1.445767193805684
  },
  {
    "date": "2024-06-18",
    "strategy": 1.3867367943166198,
    "benchmark": 1.4494406737519765
  },
  {
    "date": "2024-06-20",
    "strategy": 1.3831729813940343,
    "benchmark": 1.4455032370945846
  },
  {
    "date": "2024-06-21",
    "strategy": 1.3777027622525764,
    "benchmark": 1.4435654125757085
  },
  {
    "date": "2024-06-24",
    "strategy": 1.371506712011483,
    "benchmark": 1.4388726840558448
  },
  {
    "date": "2024-06-25",
    "strategy": 1.3854735054787028,
    "benchmark": 1.4444136330181176
  },
  {
    "date": "2024-06-26",
    "strategy": 1.382156396699565,
    "benchmark": 1.44621618384173
  },
  {
    "date": "2024-06-27",
    "strategy": 1.3857265324523471,
    "benchmark": 1.4484963941569013
  },
  {
    "date": "2024-06-28",
    "strategy": 1.3661336136609565,
    "benchmark": 1.4427964450534232
  },
  {
    "date": "2024-07-01",
    "strategy": 1.37874157722028,
    "benchmark": 1.445765546135827
  },
  {
    "date": "2024-07-02",
    "strategy": 1.3854697650893046,
    "benchmark": 1.4554953661756775
  },
  {
    "date": "2024-07-03",
    "strategy": 1.4043636758322298,
    "benchmark": 1.4619908102861392
  },
  {
    "date": "2024-07-05",
    "strategy": 1.4034201046721255,
    "benchmark": 1.4704211131097347
  },
  {
    "date": "2024-07-08",
    "strategy": 1.4101475928985672,
    "benchmark": 1.4721178835285245
  },
  {
    "date": "2024-07-09",
    "strategy": 1.420265445460779,
    "benchmark": 1.4735495438673152
  },
  {
    "date": "2024-07-10",
    "strategy": 1.4234321105587586,
    "benchmark": 1.488130763034263
  },
  {
    "date": "2024-07-11",
    "strategy": 1.4023275464972322,
    "benchmark": 1.4752992044885163
  },
  {
    "date": "2024-07-12",
    "strategy": 1.4171018141740959,
    "benchmark": 1.4846047495401766
  },
  {
    "date": "2024-07-15",
    "strategy": 1.429974909557916,
    "benchmark": 1.4886875106789603
  },
  {
    "date": "2024-07-16",
    "strategy": 1.4348669679426551,
    "benchmark": 1.4975155610060475
  },
  {
    "date": "2024-07-17",
    "strategy": 1.3777151911528525,
    "benchmark": 1.4765188097167046
  },
  {
    "date": "2024-07-18",
    "strategy": 1.3702635516742632,
    "benchmark": 1.4651719664791454
  },
  {
    "date": "2024-07-19",
    "strategy": 1.3579837680347677,
    "benchmark": 1.4554423112062804
  },
  {
    "date": "2024-07-22",
    "strategy": 1.3810119588441832,
    "benchmark": 1.470447805361419
  },
  {
    "date": "2024-07-23",
    "strategy": 1.3867558157541842,
    "benchmark": 1.4681412323285348
  },
  {
    "date": "2024-07-24",
    "strategy": 1.3245128886783613,
    "benchmark": 1.4348695053711567
  },
  {
    "date": "2024-07-25",
    "strategy": 1.3133429188165573,
    "benchmark": 1.4273933681617788
  },
  {
    "date": "2024-07-26",
    "strategy": 1.3291262485407425,
    "benchmark": 1.443379720182819
  },
  {
    "date": "2024-07-29",
    "strategy": 1.3260865497423115,
    "benchmark": 1.444227940625228
  },
  {
    "date": "2024-07-30",
    "strategy": 1.2997967416845975,
    "benchmark": 1.436911133091027
  },
  {
    "date": "2024-07-31",
    "strategy": 1.3537646181902572,
    "benchmark": 1.4602673476156651
  },
  {
    "date": "2024-08-01",
    "strategy": 1.3726277737481325,
    "benchmark": 1.4395884318417473
  },
  {
    "date": "2024-08-02",
    "strategy": 1.352540665026214,
    "benchmark": 1.412785786277118
  },
  {
    "date": "2024-08-05",
    "strategy": 1.3214575716427908,
    "benchmark": 1.371640256990363
  },
  {
    "date": "2024-08-06",
    "strategy": 1.3485875454244372,
    "benchmark": 1.384286205526713
  },
  {
    "date": "2024-08-07",
    "strategy": 1.3472863152766192,
    "benchmark": 1.3750334682939713
  },
  {
    "date": "2024-08-08",
    "strategy": 1.3680361984649159,
    "benchmark": 1.4068207270936406
  },
  {
    "date": "2024-08-09",
    "strategy": 1.3798072112760214,
    "benchmark": 1.413024204105433
  },
  {
    "date": "2024-08-12",
    "strategy": 1.3730778106858144,
    "benchmark": 1.4137668089100055
  },
  {
    "date": "2024-08-13",
    "strategy": 1.3882143726471856,
    "benchmark": 1.4370170782628353
  },
  {
    "date": "2024-08-14",
    "strategy": 1.3994664469551108,
    "benchmark": 1.4415504771075223
  },
  {
    "date": "2024-08-15",
    "strategy": 1.3940723873198309,
    "benchmark": 1.4662587695168554
  },
  {
    "date": "2024-08-16",
    "strategy": 1.40087408399514,
    "benchmark": 1.4695460356486556
  },
  {
    "date": "2024-08-19",
    "strategy": 1.4081924167778148,
    "benchmark": 1.4835973641895763
  },
  {
    "date": "2024-08-20",
    "strategy": 1.4039794196934088,
    "benchmark": 1.4811846812178981
  },
  {
    "date": "2024-08-21",
    "strategy": 1.4131667594843247,
    "benchmark": 1.4862748277072821
  },
  {
    "date": "2024-08-22",
    "strategy": 1.4211979254382732,
    "benchmark": 1.4746098194203268
  },
  {
    "date": "2024-08-23",
    "strategy": 1.432642989427603,
    "benchmark": 1.4902778416249847
  },
  {
    "date": "2024-08-26",
    "strategy": 1.4301599565172185,
    "benchmark": 1.4867254654131854
  },
  {
    "date": "2024-08-27",
    "strategy": 1.4347586084080213,
    "benchmark": 1.48876692836607
  },
  {
    "date": "2024-08-28",
    "strategy": 1.4371270238447902,
    "benchmark": 1.480124240897901
  },
  {
    "date": "2024-08-29",
    "strategy": 1.4414594871195816,
    "benchmark": 1.4802567135544078
  },
  {
    "date": "2024-08-30",
    "strategy": 1.4513169591790713,
    "benchmark": 1.4943872950154526
  },
  {
    "date": "2024-09-03",
    "strategy": 1.4469939104167984,
    "benchmark": 1.4636343609685465
  },
  {
    "date": "2024-09-04",
    "strategy": 1.4501472480333006,
    "benchmark": 1.4606385676344584
  },
  {
    "date": "2024-09-05",
    "strategy": 1.4391323617635783,
    "benchmark": 1.4570858618886877
  },
  {
    "date": "2024-09-06",
    "strategy": 1.4225759121580293,
    "benchmark": 1.432563261872244
  },
  {
    "date": "2024-09-09",
    "strategy": 1.4433549659628977,
    "benchmark": 1.448602174561724
  },
  {
    "date": "2024-09-10",
    "strategy": 1.4413801185318573,
    "benchmark": 1.4549120910462818
  },
  {
    "date": "2024-09-11",
    "strategy": 1.438978150010272,
    "benchmark": 1.469837837980339
  },
  {
    "date": "2024-09-12",
    "strategy": 1.4466743595913256,
    "benchmark": 1.4822187588201827
  },
  {
    "date": "2024-09-13",
    "strategy": 1.4543695922737274,
    "benchmark": 1.48996000610956
  },
  {
    "date": "2024-09-16",
    "strategy": 1.4695206597847261,
    "benchmark": 1.4921603044366643
  },
  {
    "date": "2024-09-17",
    "strategy": 1.4630937185713695,
    "benchmark": 1.492770271817744
  },
  {
    "date": "2024-09-18",
    "strategy": 1.4661078281856799,
    "benchmark": 1.4883428181448655
  },
  {
    "date": "2024-09-19",
    "strategy": 1.4634806735874704,
    "benchmark": 1.5137404956223883
  },
  {
    "date": "2024-09-20",
    "strategy": 1.4657436449399945,
    "benchmark": 1.5111239958893932
  },
  {
    "date": "2024-09-23",
    "strategy": 1.4811183425783592,
    "benchmark": 1.5148999609007943
  },
  {
    "date": "2024-09-24",
    "strategy": 1.4764155309564064,
    "benchmark": 1.5192346507607208
  },
  {
    "date": "2024-09-25",
    "strategy": 1.478505009144331,
    "benchmark": 1.5158839493394245
  },
  {
    "date": "2024-09-26",
    "strategy": 1.4679642912165216,
    "benchmark": 1.5218939899099992
  },
  {
    "date": "2024-09-27",
    "strategy": 1.4632920688448947,
    "benchmark": 1.519686441835524
  },
  {
    "date": "2024-09-30",
    "strategy": 1.4739525352908986,
    "benchmark": 1.5257762296271802
  },
  {
    "date": "2024-10-01",
    "strategy": 1.4810883091721934,
    "benchmark": 1.512107654794052
  },
  {
    "date": "2024-10-02",
    "strategy": 1.4866937927784263,
    "benchmark": 1.512745962096673
  },
  {
    "date": "2024-10-03",
    "strategy": 1.4952020528238588,
    "benchmark": 1.5099805130086006
  },
  {
    "date": "2024-10-04",
    "strategy": 1.5130425769601326,
    "benchmark": 1.52370197804414
  },
  {
    "date": "2024-10-07",
    "strategy": 1.4996696771502767,
    "benchmark": 1.5099272932722179
  },
  {
    "date": "2024-10-08",
    "strategy": 1.5150122280719196,
    "benchmark": 1.5242073183892972
  },
  {
    "date": "2024-10-09",
    "strategy": 1.5058769489978034,
    "benchmark": 1.5347645982313582
  },
  {
    "date": "2024-10-10",
    "strategy": 1.4902083734885887,
    "benchmark": 1.532078896364367
  },
  {
    "date": "2024-10-11",
    "strategy": 1.507957633422005,
    "benchmark": 1.541253286895406
  },
  {
    "date": "2024-10-14",
    "strategy": 1.5186185186571237,
    "benchmark": 1.553858126068823
  },
  {
    "date": "2024-10-15",
    "strategy": 1.5096771785952543,
    "benchmark": 1.541784989958276
  },
  {
    "date": "2024-10-16",
    "strategy": 1.5339213411148516,
    "benchmark": 1.5484865575678548
  },
  {
    "date": "2024-10-17",
    "strategy": 1.5224985142789784,
    "benchmark": 1.5486191949913473
  },
  {
    "date": "2024-10-18",
    "strategy": 1.527753897120735,
    "benchmark": 1.5545761805925251
  },
  {
    "date": "2024-10-21",
    "strategy": 1.5300037551532397,
    "benchmark": 1.5520231161490265
  },
  {
    "date": "2024-10-22",
    "strategy": 1.5139397871383733,
    "benchmark": 1.55119895168653
  },
  {
    "date": "2024-10-23",
    "strategy": 1.523491032156586,
    "benchmark": 1.537025036508245
  },
  {
    "date": "2024-10-24",
    "strategy": 1.548732265003055,
    "benchmark": 1.5403492104448429
  },
  {
    "date": "2024-10-25",
    "strategy": 1.5425920531295796,
    "benchmark": 1.5398173426149873
  },
  {
    "date": "2024-10-28",
    "strategy": 1.5482755649666504,
    "benchmark": 1.544577460832004
  },
  {
    "date": "2024-10-29",
    "strategy": 1.5399104075499146,
    "benchmark": 1.5470769760051486
  },
  {
    "date": "2024-10-30",
    "strategy": 1.5315645537183766,
    "benchmark": 1.5423967697761987
  },
  {
    "date": "2024-10-31",
    "strategy": 1.5422290527162077,
    "benchmark": 1.5121610392974203
  },
  {
    "date": "2024-11-01",
    "strategy": 1.5271870312587874,
    "benchmark": 1.518543123721717
  },
  {
    "date": "2024-11-04",
    "strategy": 1.5286239273271198,
    "benchmark": 1.515272169521502
  },
  {
    "date": "2024-11-05",
    "strategy": 1.5770400831944995,
    "benchmark": 1.5335945878658672
  },
  {
    "date": "2024-11-06",
    "strategy": 1.6737997570789156,
    "benchmark": 1.5717285885713994
  },
  {
    "date": "2024-11-07",
    "strategy": 1.7096647921555381,
    "benchmark": 1.583881142369056
  },
  {
    "date": "2024-11-08",
    "strategy": 1.7521697033094128,
    "benchmark": 1.590742204420797
  },
  {
    "date": "2024-11-11",
    "strategy": 1.7923398766789715,
    "benchmark": 1.5922575663883258
  },
  {
    "date": "2024-11-12",
    "strategy": 1.7844780778802596,
    "benchmark": 1.5873115910114337
  },
  {
    "date": "2024-11-13",
    "strategy": 1.7706672906331078,
    "benchmark": 1.588082700504533
  },
  {
    "date": "2024-11-14",
    "strategy": 1.7623636540107148,
    "benchmark": 1.5778714313324524
  },
  {
    "date": "2024-11-15",
    "strategy": 1.7536316061468957,
    "benchmark": 1.5576609480988939
  },
  {
    "date": "2024-11-18",
    "strategy": 1.769224792146187,
    "benchmark": 1.5640431972901763
  },
  {
    "date": "2024-11-19",
    "strategy": 1.7929530885987617,
    "benchmark": 1.5697604469271533
  },
  {
    "date": "2024-11-20",
    "strategy": 1.7813783580420588,
    "benchmark": 1.5702921499900233
  },
  {
    "date": "2024-11-21",
    "strategy": 1.812004801332139,
    "benchmark": 1.5787221232796473
  },
  {
    "date": "2024-11-22",
    "strategy": 1.834039895474749,
    "benchmark": 1.5836152084541282
  },
  {
    "date": "2024-11-25",
    "strategy": 1.8414534025719917,
    "benchmark": 1.5889871064890677
  },
  {
    "date": "2024-11-26",
    "strategy": 1.8604597322263399,
    "benchmark": 1.5972837832872562
  },
  {
    "date": "2024-11-27",
    "strategy": 1.8490667761676798,
    "benchmark": 1.592443917849158
  },
  {
    "date": "2024-11-29",
    "strategy": 1.8646888111026736,
    "benchmark": 1.6023363629038996
  },
  {
    "date": "2024-12-02",
    "strategy": 1.8728861557159162,
    "benchmark": 1.6052085809987087
  },
  {
    "date": "2024-12-03",
    "strategy": 1.8698401716396915,
    "benchmark": 1.6059529982401237
  },
  {
    "date": "2024-12-04",
    "strategy": 1.8902252209450867,
    "benchmark": 1.615925355282932
  },
  {
    "date": "2024-12-05",
    "strategy": 1.8826104634423837,
    "benchmark": 1.613265851366668
  },
  {
    "date": "2024-12-06",
    "strategy": 1.898827591328273,
    "benchmark": 1.616324256155324
  },
  {
    "date": "2024-12-09",
    "strategy": 1.8302379831073265,
    "benchmark": 1.6080005575714795
  },
  {
    "date": "2024-12-10",
    "strategy": 1.8185018783233136,
    "benchmark": 1.603001197691219
  },
  {
    "date": "2024-12-11",
    "strategy": 1.8677574657807041,
    "benchmark": 1.6153934874530764
  },
  {
    "date": "2024-12-12",
    "strategy": 1.8517219343177156,
    "benchmark": 1.6070699536362179
  },
  {
    "date": "2024-12-13",
    "strategy": 1.8512966530608468,
    "benchmark": 1.6067507999849073
  },
  {
    "date": "2024-12-16",
    "strategy": 1.8701833678033688,
    "benchmark": 1.613611532502677
  },
  {
    "date": "2024-12-17",
    "strategy": 1.850411049638691,
    "benchmark": 1.6069635141634524
  },
  {
    "date": "2024-12-18",
    "strategy": 1.7491210575248926,
    "benchmark": 1.5590703648946143
  },
  {
    "date": "2024-12-19",
    "strategy": 1.7537148411667827,
    "benchmark": 1.5585915520341556
  },
  {
    "date": "2024-12-20",
    "strategy": 1.8082728136071926,
    "benchmark": 1.5773118826489985
  },
  {
    "date": "2024-12-23",
    "strategy": 1.793112353539219,
    "benchmark": 1.5867573148715222
  },
  {
    "date": "2024-12-24",
    "strategy": 1.815152539355447,
    "benchmark": 1.604394137788369
  },
  {
    "date": "2024-12-26",
    "strategy": 1.8125717912435286,
    "benchmark": 1.6045010715620915
  },
  {
    "date": "2024-12-27",
    "strategy": 1.7774650785434474,
    "benchmark": 1.5876111373914454
  },
  {
    "date": "2024-12-30",
    "strategy": 1.7667750800203812,
    "benchmark": 1.5694940187112685
  },
  {
    "date": "2024-12-31",
    "strategy": 1.7473071217109324,
    "benchmark": 1.5637838540546767
  },
  {
    "date": "2025-01-02",
    "strategy": 1.763707885613257,
    "benchmark": 1.5599418174820079
  },
  {
    "date": "2025-01-03",
    "strategy": 1.7850847861675956,
    "benchmark": 1.5794464389488063
  },
  {
    "date": "2025-01-06",
    "strategy": 1.8049250579804694,
    "benchmark": 1.5885448718994355
  },
  {
    "date": "2025-01-07",
    "strategy": 1.785575230909158,
    "benchmark": 1.5705877419623782
  },
  {
    "date": "2025-01-08",
    "strategy": 1.785199453935781,
    "benchmark": 1.5728824517722915
  },
  {
    "date": "2025-01-10",
    "strategy": 1.7443708135915013,
    "benchmark": 1.5488686522077046
  },
  {
    "date": "2025-01-13",
    "strategy": 1.7394725986448087,
    "benchmark": 1.5512701310243546
  },
  {
    "date": "2025-01-14",
    "strategy": 1.7530893639519303,
    "benchmark": 1.553404522557177
  },
  {
    "date": "2025-01-15",
    "strategy": 1.7705082800824414,
    "benchmark": 1.581661072003667
  },
  {
    "date": "2025-01-16",
    "strategy": 1.7761714983471033,
    "benchmark": 1.5786193086805673
  },
  {
    "date": "2025-01-17",
    "strategy": 1.7968851388295115,
    "benchmark": 1.5944685745695009
  },
  {
    "date": "2025-01-21",
    "strategy": 1.8250627437767568,
    "benchmark": 1.6090634693962624
  },
  {
    "date": "2025-01-22",
    "strategy": 1.8744998746814725,
    "benchmark": 1.6181088473774945
  },
  {
    "date": "2025-01-23",
    "strategy": 1.9063504849734507,
    "benchmark": 1.6269405225782672
  },
  {
    "date": "2025-01-24",
    "strategy": 1.926353954993776,
    "benchmark": 1.6221909494483353
  },
  {
    "date": "2025-01-27",
    "strategy": 1.8940571048175745,
    "benchmark": 1.5992445104171455
  },
  {
    "date": "2025-01-28",
    "strategy": 1.929635830077317,
    "benchmark": 1.6129857474909695
  },
  {
    "date": "2025-01-29",
    "strategy": 1.9410472941150478,
    "benchmark": 1.6057549483233065
  },
  {
    "date": "2025-01-30",
    "strategy": 1.965929881236912,
    "benchmark": 1.6143732502775912
  },
  {
    "date": "2025-01-31",
    "strategy": 1.945842222124196,
    "benchmark": 1.6057816405749907
  },
  {
    "date": "2025-02-03",
    "strategy": 1.959789372173878,
    "benchmark": 1.5949753978175294
  },
  {
    "date": "2025-02-04",
    "strategy": 1.9995951097267488,
    "benchmark": 1.6056750363352394
  },
  {
    "date": "2025-02-05",
    "strategy": 2.0142003057670976,
    "benchmark": 1.6121853094744147
  },
  {
    "date": "2025-02-06",
    "strategy": 2.0090777973646676,
    "benchmark": 1.617788540357284
  },
  {
    "date": "2025-02-07",
    "strategy": 2.014158495830661,
    "benchmark": 1.602979942750063
  },
  {
    "date": "2025-02-10",
    "strategy": 2.0208805841185047,
    "benchmark": 1.6138664270295626
  },
  {
    "date": "2025-02-11",
    "strategy": 2.020473580521629,
    "benchmark": 1.615093776306079
  },
  {
    "date": "2025-02-12",
    "strategy": 2.052793199680303,
    "benchmark": 1.6098905996645014
  },
  {
    "date": "2025-02-13",
    "strategy": 2.0920125449228997,
    "benchmark": 1.6268871380748988
  },
  {
    "date": "2025-02-14",
    "strategy": 2.0997005430083235,
    "benchmark": 1.6268070613198462
  },
  {
    "date": "2025-02-18",
    "strategy": 2.091753954550496,
    "benchmark": 1.6315831619344765
  },
  {
    "date": "2025-02-19",
    "strategy": 2.0844454795448253,
    "benchmark": 1.6354255280411165
  },
  {
    "date": "2025-02-20",
    "strategy": 2.0403310385907987,
    "benchmark": 1.6286214753664294
  },
  {
    "date": "2025-02-21",
    "strategy": 1.9909673128356837,
    "benchmark": 1.6007653096952026
  },
  {
    "date": "2025-02-24",
    "strategy": 1.9985906751827354,
    "benchmark": 1.593481126024171
  },
  {
    "date": "2025-02-25",
    "strategy": 1.9351988897707244,
    "benchmark": 1.58555665784669
  },
  {
    "date": "2025-02-26",
    "strategy": 1.9535070730434496,
    "benchmark": 1.586356931096259
  },
  {
    "date": "2025-02-27",
    "strategy": 1.9243849961611934,
    "benchmark": 1.5610357055001032
  },
  {
    "date": "2025-02-28",
    "strategy": 1.9614125165856402,
    "benchmark": 1.5853965043365847
  },
  {
    "date": "2025-03-03",
    "strategy": 1.9723130451114819,
    "benchmark": 1.5576204154204103
  },
  {
    "date": "2025-03-04",
    "strategy": 1.9166035639598917,
    "benchmark": 1.539182989720023
  },
  {
    "date": "2025-03-05",
    "strategy": 1.9157335947928695,
    "benchmark": 1.5557259246187745
  },
  {
    "date": "2025-03-06",
    "strategy": 1.882098352115077,
    "benchmark": 1.5281099892127055
  },
  {
    "date": "2025-03-07",
    "strategy": 1.888910142234216,
    "benchmark": 1.5366749066636218
  },
  {
    "date": "2025-03-10",
    "strategy": 1.8754246352720116,
    "benchmark": 1.4957446454436902
  },
  {
    "date": "2025-03-11",
    "strategy": 1.8572438550669768,
    "benchmark": 1.4833106696344496
  },
  {
    "date": "2025-03-12",
    "strategy": 1.8548151419002221,
    "benchmark": 1.491181918075548
  },
  {
    "date": "2025-03-13",
    "strategy": 1.844335728008096,
    "benchmark": 1.4713039346191419
  },
  {
    "date": "2025-03-14",
    "strategy": 1.8743715156565588,
    "benchmark": 1.5016947108314687
  },
  {
    "date": "2025-03-17",
    "strategy": 1.8948750504728733,
    "benchmark": 1.513274864120786
  },
  {
    "date": "2025-03-18",
    "strategy": 1.8752893770259735,
    "benchmark": 1.4969186102168384
  },
  {
    "date": "2025-03-19",
    "strategy": 1.888746459277514,
    "benchmark": 1.5132213148504319
  },
  {
    "date": "2025-03-20",
    "strategy": 1.886587357108,
    "benchmark": 1.5088455980110647
  },
  {
    "date": "2025-03-21",
    "strategy": 1.8860109763349084,
    "benchmark": 1.5093433590748795
  },
  {
    "date": "2025-03-24",
    "strategy": 1.8930675351402046,
    "benchmark": 1.536373218312796
  },
  {
    "date": "2025-03-25",
    "strategy": 1.904264547763248,
    "benchmark": 1.5400666350643588
  },
  {
    "date": "2025-03-26",
    "strategy": 1.9198428013234907,
    "benchmark": 1.5216809461974827
  },
  {
    "date": "2025-03-27",
    "strategy": 1.928010442915507,
    "benchmark": 1.5176395415721111
  },
  {
    "date": "2025-03-28",
    "strategy": 1.922166238838929,
    "benchmark": 1.4870770781606797
  },
  {
    "date": "2025-03-31",
    "strategy": 1.9462016955440016,
    "benchmark": 1.497059485989616
  },
  {
    "date": "2025-04-01",
    "strategy": 1.95002951284624,
    "benchmark": 1.501287901143763
  },
  {
    "date": "2025-04-02",
    "strategy": 1.9504740036027317,
    "benchmark": 1.5107885303064978
  },
  {
    "date": "2025-04-03",
    "strategy": 1.9285022737568485,
    "benchmark": 1.4363357667769452
  },
  {
    "date": "2025-04-04",
    "strategy": 1.803937983160882,
    "benchmark": 1.3522483361417865
  },
  {
    "date": "2025-04-07",
    "strategy": 1.7950097372128953,
    "benchmark": 1.3498396899612584
  },
  {
    "date": "2025-04-08",
    "strategy": 1.7857248704295792,
    "benchmark": 1.328697449423538
  },
  {
    "date": "2025-04-09",
    "strategy": 1.8401044313405857,
    "benchmark": 1.4682364676462722
  },
  {
    "date": "2025-04-10",
    "strategy": 1.8214032696713771,
    "benchmark": 1.4038997379710627
  },
  {
    "date": "2025-04-11",
    "strategy": 1.8475569473712532,
    "benchmark": 1.4289494275747767
  },
  {
    "date": "2025-04-14",
    "strategy": 1.877434018448968,
    "benchmark": 1.442812097917065
  },
  {
    "date": "2025-04-15",
    "strategy": 1.8961746133990602,
    "benchmark": 1.438770858058679
  },
  {
    "date": "2025-04-16",
    "strategy": 1.8908334881503097,
    "benchmark": 1.4067899156673138
  },
  {
    "date": "2025-04-17",
    "strategy": 1.9092164109904164,
    "benchmark": 1.4087971070871719
  },
  {
    "date": "2025-04-21",
    "strategy": 1.8597716313072075,
    "benchmark": 1.3752638949234797
  },
  {
    "date": "2025-04-22",
    "strategy": 1.9051820590742572,
    "benchmark": 1.4110453526071163
  },
  {
    "date": "2025-04-23",
    "strategy": 1.9114973882149893,
    "benchmark": 1.4329099316101672
  },
  {
    "date": "2025-04-24",
    "strategy": 1.9284254317959895,
    "benchmark": 1.4630711874114068
  },
  {
    "date": "2025-04-25",
    "strategy": 1.9260251963889752,
    "benchmark": 1.4736424724472528
  },
  {
    "date": "2025-04-28",
    "strategy": 1.936070608070327,
    "benchmark": 1.4742044926354925
  },
  {
    "date": "2025-04-29",
    "strategy": 1.9450897716958084,
    "benchmark": 1.4834909247168109
  },
  {
    "date": "2025-04-30",
    "strategy": 1.937105487663278,
    "benchmark": 1.4840796371567349
  },
  {
    "date": "2025-05-01",
    "strategy": 1.9427472413281084,
    "benchmark": 1.4945973729222266
  },
  {
    "date": "2025-05-02",
    "strategy": 1.9504433283002724,
    "benchmark": 1.516783412314388
  },
  {
    "date": "2025-05-05",
    "strategy": 1.9582282780052607,
    "benchmark": 1.5080855279060077
  },
  {
    "date": "2025-05-06",
    "strategy": 1.9697359973386421,
    "benchmark": 1.4954805239656053
  },
  {
    "date": "2025-05-07",
    "strategy": 1.9753792602856943,
    "benchmark": 1.5017696798099645
  },
  {
    "date": "2025-05-08",
    "strategy": 1.9529441804256975,
    "benchmark": 1.5122337015381162
  },
  {
    "date": "2025-05-09",
    "strategy": 1.9375752166337452,
    "benchmark": 1.5103069164072822
  },
  {
    "date": "2025-05-12",
    "strategy": 1.912143733646787,
    "benchmark": 1.5602186260179922
  },
  {
    "date": "2025-05-13",
    "strategy": 1.9053727256984687,
    "benchmark": 1.570521999935082
  },
  {
    "date": "2025-05-14",
    "strategy": 1.9026368357073165,
    "benchmark": 1.57252919135494
  },
  {
    "date": "2025-05-15",
    "strategy": 1.944082249533109,
    "benchmark": 1.580210133927549
  },
  {
    "date": "2025-05-16",
    "strategy": 1.963544800466625,
    "benchmark": 1.5902192340081696
  },
  {
    "date": "2025-05-19",
    "strategy": 1.98410578631443,
    "benchmark": 1.5919588438432426
  },
  {
    "date": "2025-05-20",
    "strategy": 1.986378184870143,
    "benchmark": 1.5866062235456306
  },
  {
    "date": "2025-05-21",
    "strategy": 1.9644742764401442,
    "benchmark": 1.5598706381441834
  },
  {
    "date": "2025-05-22",
    "strategy": 1.9559953841601023,
    "benchmark": 1.560486207602777
  },
  {
    "date": "2025-05-23",
    "strategy": 1.9731487977314686,
    "benchmark": 1.5498348458118787
  },
  {
    "date": "2025-05-27",
    "strategy": 1.9807601065219762,
    "benchmark": 1.5820566775363447
  },
  {
    "date": "2025-05-28",
    "strategy": 1.9699917987759377,
    "benchmark": 1.572903871480433
  },
  {
    "date": "2025-05-29",
    "strategy": 1.9615039828851693,
    "benchmark": 1.5791127858027538
  },
  {
    "date": "2025-05-30",
    "strategy": 1.9834012093128155,
    "benchmark": 1.5773466484829821
  },
  {
    "date": "2025-06-02",
    "strategy": 2.0023241694074767,
    "benchmark": 1.586231872954109
  },
  {
    "date": "2025-06-03",
    "strategy": 2.029432587605674,
    "benchmark": 1.595277250935341
  },
  {
    "date": "2025-06-04",
    "strategy": 2.0449485812900714,
    "benchmark": 1.5948491863064795
  },
  {
    "date": "2025-06-05",
    "strategy": 2.0477352810236087,
    "benchmark": 1.5871413867152004
  },
  {
    "date": "2025-06-06",
    "strategy": 2.0597617204939493,
    "benchmark": 1.6034398074071659
  },
  {
    "date": "2025-06-09",
    "strategy": 2.0334276699729537,
    "benchmark": 1.6048849786387842
  },
  {
    "date": "2025-06-10",
    "strategy": 1.9985706056459391,
    "benchmark": 1.6139844001913275
  },
  {
    "date": "2025-06-11",
    "strategy": 2.02882231865427,
    "benchmark": 1.609380975377716
  },
  {
    "date": "2025-06-12",
    "strategy": 2.0273257741705093,
    "benchmark": 1.6157770649957977
  },
  {
    "date": "2025-06-13",
    "strategy": 1.9983940411029466,
    "benchmark": 1.5977126717510464
  },
  {
    "date": "2025-06-16",
    "strategy": 2.0291140124859406,
    "benchmark": 1.6129137443182164
  },
  {
    "date": "2025-06-17",
    "strategy": 2.0408958167050715,
    "benchmark": 1.5991311507309804
  },
  {
    "date": "2025-06-18",
    "strategy": 2.04799618031648,
    "benchmark": 1.598890096630894
  },
  {
    "date": "2025-06-20",
    "strategy": 2.050986411534701,
    "benchmark": 1.5951350570266776
  },
  {
    "date": "2025-06-23",
    "strategy": 2.0840868619834088,
    "benchmark": 1.610891064801702
  },
  {
    "date": "2025-06-24",
    "strategy": 2.1195228127269368,
    "benchmark": 1.6286868878597542
  },
  {
    "date": "2025-06-25",
    "strategy": 2.1165838676119235,
    "benchmark": 1.6295995321935741
  },
  {
    "date": "2025-06-26",
    "strategy": 2.141103338236977,
    "benchmark": 1.6423492015474257
  },
  {
    "date": "2025-06-27",
    "strategy": 2.1688658287693934,
    "benchmark": 1.6505089569804934
  },
  {
    "date": "2025-06-30",
    "strategy": 2.2075456935545463,
    "benchmark": 1.6584004717608334
  },
  {
    "date": "2025-07-01",
    "strategy": 2.1836511821136613,
    "benchmark": 1.6578636609214066
  },
  {
    "date": "2025-07-02",
    "strategy": 2.212980689732768,
    "benchmark": 1.665379177440368
  },
  {
    "date": "2025-07-03",
    "strategy": 2.234399983556337,
    "benchmark": 1.6785046802886125
  },
  {
    "date": "2025-07-07",
    "strategy": 2.2314372959332625,
    "benchmark": 1.6659965593358046
  },
  {
    "date": "2025-07-08",
    "strategy": 2.2052099359436426,
    "benchmark": 1.6650840797689703
  },
  {
    "date": "2025-07-09",
    "strategy": 2.2188722343778964,
    "benchmark": 1.6750689591026922
  },
  {
    "date": "2025-07-10",
    "strategy": 2.21704262960872,
    "benchmark": 1.6797931581168255
  },
  {
    "date": "2025-07-11",
    "strategy": 2.214894470420599,
    "benchmark": 1.6738879093491588
  },
  {
    "date": "2025-07-14",
    "strategy": 2.2300487265372397,
    "benchmark": 1.67708191736705
  },
  {
    "date": "2025-07-15",
    "strategy": 2.218469950525843,
    "benchmark": 1.6699153773238118
  },
  {
    "date": "2025-07-16",
    "strategy": 2.2257549966280603,
    "benchmark": 1.6754983418674394
  },
  {
    "date": "2025-07-17",
    "strategy": 2.2427453396936636,
    "benchmark": 1.6857517913878604
  },
  {
    "date": "2025-07-18",
    "strategy": 2.268824538100091,
    "benchmark": 1.684517192363973
  },
  {
    "date": "2025-07-21",
    "strategy": 2.259969880667887,
    "benchmark": 1.6877113651488496
  },
  {
    "date": "2025-07-22",
    "strategy": 2.239152687868446,
    "benchmark": 1.6879529135498932
  },
  {
    "date": "2025-07-23",
    "strategy": 2.265281737224686,
    "benchmark": 1.7023131801890108
  },
  {
    "date": "2025-07-24",
    "strategy": 2.2465340517834083,
    "benchmark": 1.7028766832801219
  },
  {
    "date": "2025-07-25",
    "strategy": 2.3249612865518086,
    "benchmark": 1.7100702451090155
  },
  {
    "date": "2025-07-28",
    "strategy": 2.3374738924608427,
    "benchmark": 1.7096408623442685
  },
  {
    "date": "2025-07-29",
    "strategy": 2.290187716814909,
    "benchmark": 1.7051313547125089
  },
  {
    "date": "2025-07-30",
    "strategy": 2.2723664670801496,
    "benchmark": 1.7029841113548014
  },
  {
    "date": "2025-07-31",
    "strategy": 2.2748360698200276,
    "benchmark": 1.6965959305520337
  },
  {
    "date": "2025-08-01",
    "strategy": 2.2241830564350655,
    "benchmark": 1.6687878768406326
  },
  {
    "date": "2025-08-04",
    "strategy": 2.299562310339502,
    "benchmark": 1.6941530952219717
  },
  {
    "date": "2025-08-05",
    "strategy": 2.2959596783149956,
    "benchmark": 1.685563792257171
  },
  {
    "date": "2025-08-06",
    "strategy": 2.3252569540847223,
    "benchmark": 1.6984747684900277
  },
  {
    "date": "2025-08-07",
    "strategy": 2.2948869329505244,
    "benchmark": 1.697052005568465
  },
  {
    "date": "2025-08-08",
    "strategy": 2.318419439493181,
    "benchmark": 1.7102849364913892
  },
  {
    "date": "2025-08-11",
    "strategy": 2.309819130627891,
    "benchmark": 1.7069029293428089
  },
  {
    "date": "2025-08-12",
    "strategy": 2.355727050674568,
    "benchmark": 1.7250747506622397
  },
  {
    "date": "2025-08-13",
    "strategy": 2.3314449554315275,
    "benchmark": 1.7309798346629206
  },
  {
    "date": "2025-08-14",
    "strategy": 2.281081448864261,
    "benchmark": 1.7311408120079543
  },
  {
    "date": "2025-08-15",
    "strategy": 2.2817110537148944,
    "benchmark": 1.727087873693583
  },
  {
    "date": "2025-08-18",
    "strategy": 2.2853240629616356,
    "benchmark": 1.7267118754322044
  },
  {
    "date": "2025-08-19",
    "strategy": 2.2157545309017124,
    "benchmark": 1.7173442132269334
  },
  {
    "date": "2025-08-20",
    "strategy": 2.210090125629756,
    "benchmark": 1.7127811563248196
  },
  {
    "date": "2025-08-21",
    "strategy": 2.2085325000177294,
    "benchmark": 1.705909713952979
  },
  {
    "date": "2025-08-22",
    "strategy": 2.23062154387586,
    "benchmark": 1.732107170379114
  },
  {
    "date": "2025-08-25",
    "strategy": 2.2335082700675297,
    "benchmark": 1.7244838962515017
  },
  {
    "date": "2025-08-26",
    "strategy": 2.267044468286904,
    "benchmark": 1.731704479866051
  },
  {
    "date": "2025-08-27",
    "strategy": 2.265606327506589,
    "benchmark": 1.7356501548727281
  },
  {
    "date": "2025-08-28",
    "strategy": 2.296428139728368,
    "benchmark": 1.7417967872744526
  },
  {
    "date": "2025-08-29",
    "strategy": 2.2494969959599733,
    "benchmark": 1.7314092174276676
  },
  {
    "date": "2025-09-02",
    "strategy": 2.2481454874855644,
    "benchmark": 1.7185789770178066
  },
  {
    "date": "2025-09-03",
    "strategy": 2.26945464678224,
    "benchmark": 1.7278929251857378
  },
  {
    "date": "2025-09-04",
    "strategy": 2.3040282881032503,
    "benchmark": 1.7423335981138794
  },
  {
    "date": "2025-09-05",
    "strategy": 2.294469886249909,
    "benchmark": 1.7372874444096786
  },
  {
    "date": "2025-09-08",
    "strategy": 2.3167775907496724,
    "benchmark": 1.741555238873409
  },
  {
    "date": "2025-09-09",
    "strategy": 2.342046242104766,
    "benchmark": 1.745581484936096
  },
  {
    "date": "2025-09-10",
    "strategy": 2.373992457954379,
    "benchmark": 1.7506278034072824
  },
  {
    "date": "2025-09-11",
    "strategy": 2.402511122483689,
    "benchmark": 1.7651759044101036
  },
  {
    "date": "2025-09-12",
    "strategy": 2.376806985050922,
    "benchmark": 1.7645852147663514
  },
  {
    "date": "2025-09-15",
    "strategy": 2.4128255913964676,
    "benchmark": 1.7739797339902923
  },
  {
    "date": "2025-09-16",
    "strategy": 2.3989669429838503,
    "benchmark": 1.7715372281942017
  },
  {
    "date": "2025-09-17",
    "strategy": 2.398993918988606,
    "benchmark": 1.7693362707991545
  },
  {
    "date": "2025-09-18",
    "strategy": 2.4589031058076087,
    "benchmark": 1.777603454306902
  },
  {
    "date": "2025-09-19",
    "strategy": 2.4821826020604614,
    "benchmark": 1.7864076134210618
  },
  {
    "date": "2025-09-22",
    "strategy": 2.486702294472571,
    "benchmark": 1.794859171185813
  },
  {
    "date": "2025-09-23",
    "strategy": 2.499080991374003,
    "benchmark": 1.7850888184674791
  },
  {
    "date": "2025-09-24",
    "strategy": 2.4711387966696106,
    "benchmark": 1.7794093004702285
  },
  {
    "date": "2025-09-25",
    "strategy": 2.4552913762612856,
    "benchmark": 1.7712001149414491
  },
  {
    "date": "2025-09-26",
    "strategy": 2.4739450706742616,
    "benchmark": 1.7813474545230763
  },
  {
    "date": "2025-09-29",
    "strategy": 2.5264996242362567,
    "benchmark": 1.7863537346167364
  },
  {
    "date": "2025-09-30",
    "strategy": 2.5373452508813967,
    "benchmark": 1.793082653545942
  },
  {
    "date": "2025-10-01",
    "strategy": 2.6094287145553667,
    "benchmark": 1.79919270767684
  },
  {
    "date": "2025-10-02",
    "strategy": 2.6036164501769203,
    "benchmark": 1.8012649820560513
  },
  {
    "date": "2025-10-03",
    "strategy": 2.586719003945434,
    "benchmark": 1.8012382898043673
  },
  {
    "date": "2025-10-06",
    "strategy": 2.5684142695090824,
    "benchmark": 1.807697979478931
  },
  {
    "date": "2025-10-07",
    "strategy": 2.5575766323116835,
    "benchmark": 1.8009959175683952
  },
  {
    "date": "2025-10-08",
    "strategy": 2.6046586967564145,
    "benchmark": 1.811735429696646
  },
  {
    "date": "2025-10-09",
    "strategy": 2.5878924103421848,
    "benchmark": 1.8064867773670137
  },
  {
    "date": "2025-10-10",
    "strategy": 2.4713410137728857,
    "benchmark": 1.7576613764930566
  },
  {
    "date": "2025-10-13",
    "strategy": 2.5518794396525184,
    "benchmark": 1.7846310957811908
  },
  {
    "date": "2025-10-14",
    "strategy": 2.5245154862454062,
    "benchmark": 1.7824508990263424
  },
  {
    "date": "2025-10-15",
    "strategy": 2.590343992559831,
    "benchmark": 1.7903641630487956
  },
  {
    "date": "2025-10-16",
    "strategy": 2.6244027745653056,
    "benchmark": 1.778171406106627
  },
  {
    "date": "2025-10-17",
    "strategy": 2.6011406922948734,
    "benchmark": 1.7882648668839285
  },
  {
    "date": "2025-10-20",
    "strategy": 2.6056449692183343,
    "benchmark": 1.8068635994633209
  },
  {
    "date": "2025-10-21",
    "strategy": 2.595755072555015,
    "benchmark": 1.8068365776776654
  },
  {
    "date": "2025-10-22",
    "strategy": 2.5858945598572696,
    "benchmark": 1.7974430470556386
  },
  {
    "date": "2025-10-23",
    "strategy": 2.686273964786817,
    "benchmark": 1.8081018233608939
  },
  {
    "date": "2025-10-24",
    "strategy": 2.7526347706115244,
    "benchmark": 1.8228786209398737
  },
  {
    "date": "2025-10-27",
    "strategy": 2.776475409416108,
    "benchmark": 1.8443843374480593
  },
  {
    "date": "2025-10-28",
    "strategy": 2.7518414938862383,
    "benchmark": 1.849283024700054
  },
  {
    "date": "2025-10-29",
    "strategy": 2.9002060020154232,
    "benchmark": 1.8501712835199897
  },
  {
    "date": "2025-10-30",
    "strategy": 2.8847154070839456,
    "benchmark": 1.8298228903193958
  },
  {
    "date": "2025-10-31",
    "strategy": 2.914081323693811,
    "benchmark": 1.8358251868416426
  },
  {
    "date": "2025-11-03",
    "strategy": 2.9679838684386155,
    "benchmark": 1.8392704645127338
  },
  {
    "date": "2025-11-04",
    "strategy": 2.8468799107991942,
    "benchmark": 1.8174684969642507
  },
  {
    "date": "2025-11-05",
    "strategy": 2.962866540591546,
    "benchmark": 1.8237668797598092
  },
  {
    "date": "2025-11-06",
    "strategy": 2.910317525048038,
    "benchmark": 1.8041989877705
  },
  {
    "date": "2025-11-07",
    "strategy": 2.9240373518229443,
    "benchmark": 1.8059753406433854
  },
  {
    "date": "2025-11-10",
    "strategy": 3.070480728769494,
    "benchmark": 1.8341564268104225
  },
  {
    "date": "2025-11-11",
    "strategy": 3.024241816022699,
    "benchmark": 1.8383551839071426
  },
  {
    "date": "2025-11-12",
    "strategy": 3.0307461046558903,
    "benchmark": 1.8393780573543992
  },
  {
    "date": "2025-11-13",
    "strategy": 2.864707702789863,
    "benchmark": 1.8088553027865228
  },
  {
    "date": "2025-11-14",
    "strategy": 2.8665156408834402,
    "benchmark": 1.8085593812801966
  },
  {
    "date": "2025-11-17",
    "strategy": 2.849264398891049,
    "benchmark": 1.7917099797880338
  },
  {
    "date": "2025-11-18",
    "strategy": 2.774297228567934,
    "benchmark": 1.7766641177213978
  },
  {
    "date": "2025-11-19",
    "strategy": 2.7967024796104005,
    "benchmark": 1.7835276512779246
  },
  {
    "date": "2025-11-20",
    "strategy": 2.583422737910323,
    "benchmark": 1.756342581539474
  },
  {
    "date": "2025-11-21",
    "strategy": 2.6092218130333036,
    "benchmark": 1.7738378696156003
  },
  {
    "date": "2025-11-24",
    "strategy": 2.748635254675256,
    "benchmark": 1.7999461871024687
  },
  {
    "date": "2025-11-25",
    "strategy": 2.762012989771039,
    "benchmark": 1.816876324417627
  },
  {
    "date": "2025-11-26",
    "strategy": 2.8065983893581463,
    "benchmark": 1.8294192112044187
  },
  {
    "date": "2025-11-28",
    "strategy": 2.8520631004442594,
    "benchmark": 1.839404914373069
  },
  {
    "date": "2025-12-01",
    "strategy": 2.8082390403919972,
    "benchmark": 1.8310072354126432
  },
  {
    "date": "2025-12-02",
    "strategy": 2.8104517399480575,
    "benchmark": 1.834398634279409
  },
  {
    "date": "2025-12-03",
    "strategy": 2.7699574829752858,
    "benchmark": 1.8407507311123072
  },
  {
    "date": "2025-12-04",
    "strategy": 2.7727684197024978,
    "benchmark": 1.8420965478515456
  },
  {
    "date": "2025-12-05",
    "strategy": 2.8197050996947346,
    "benchmark": 1.8455955395599766
  },
  {
    "date": "2025-12-08",
    "strategy": 2.852990054944717,
    "benchmark": 1.8400509657240183
  },
  {
    "date": "2025-12-09",
    "strategy": 2.85902900400184,
    "benchmark": 1.838462776748808
  },
  {
    "date": "2025-12-10",
    "strategy": 2.944458879115878,
    "benchmark": 1.850655863224948
  },
  {
    "date": "2025-12-11",
    "strategy": 2.9811446205073127,
    "benchmark": 1.8549622131633334
  },
  {
    "date": "2025-12-12",
    "strategy": 2.8886512115981513,
    "benchmark": 1.8350176638447024
  },
  {
    "date": "2025-12-15",
    "strategy": 2.8809019033174326,
    "benchmark": 1.8322452945432306
  },
  {
    "date": "2025-12-16",
    "strategy": 2.8494214694320408,
    "benchmark": 1.8272390144495703
  },
  {
    "date": "2025-12-17",
    "strategy": 2.8051745474894085,
    "benchmark": 1.8071328287179629
  },
  {
    "date": "2025-12-18",
    "strategy": 2.8431048275631725,
    "benchmark": 1.8207789952410351
  },
  {
    "date": "2025-12-19",
    "strategy": 2.9048337973983984,
    "benchmark": 1.837281562228289
  },
  {
    "date": "2025-12-22",
    "strategy": 2.9566243731857234,
    "benchmark": 1.8487275951912425
  },
  {
    "date": "2025-12-23",
    "strategy": 2.9600276351723704,
    "benchmark": 1.8571771757521653
  },
  {
    "date": "2025-12-24",
    "strategy": 2.980265573509088,
    "benchmark": 1.8637100219683822
  },
  {
    "date": "2025-12-26",
    "strategy": 2.9785688634424288,
    "benchmark": 1.8635210342357786
  },
  {
    "date": "2025-12-29",
    "strategy": 2.9725109571001314,
    "benchmark": 1.8568801008769393
  },
  {
    "date": "2025-12-30",
    "strategy": 2.9589296902031696,
    "benchmark": 1.8546125776196674
  },
  {
    "date": "2025-12-31",
    "strategy": 2.9321379187870353,
    "benchmark": 1.8408718348468005
  },
  {
    "date": "2026-01-02",
    "strategy": 3.0428305546445977,
    "benchmark": 1.8442462627140386
  },
  {
    "date": "2026-01-05",
    "strategy": 3.048826632251554,
    "benchmark": 1.8565291471973877
  },
  {
    "date": "2026-01-06",
    "strategy": 3.2417133334385917,
    "benchmark": 1.8675703476764642
  },
  {
    "date": "2026-01-07",
    "strategy": 3.2368344642751636,
    "benchmark": 1.861550421086747
  },
  {
    "date": "2026-01-08",
    "strategy": 3.135916125727715,
    "benchmark": 1.8613614333541435
  },
  {
    "date": "2026-01-09",
    "strategy": 3.1978702134092822,
    "benchmark": 1.8736713396231481
  },
  {
    "date": "2026-01-12",
    "strategy": 3.271606136771246,
    "benchmark": 1.8766137484538679
  },
  {
    "date": "2026-01-13",
    "strategy": 3.3164407220127137,
    "benchmark": 1.8728615098884083
  },
  {
    "date": "2026-01-14",
    "strategy": 3.3188562258486707,
    "benchmark": 1.863655978397071
  },
  {
    "date": "2026-01-15",
    "strategy": 3.3163980180853097,
    "benchmark": 1.8687311310907557
  },
  {
    "date": "2026-01-16",
    "strategy": 3.3183316245189634,
    "benchmark": 1.8671653504256014
  },
  {
    "date": "2026-01-20",
    "strategy": 3.352603234647608,
    "benchmark": 1.829155913561262
  },
  {
    "date": "2026-01-21",
    "strategy": 3.4390824918771212,
    "benchmark": 1.8502663540707414
  },
  {
    "date": "2026-01-22",
    "strategy": 3.453291859497616,
    "benchmark": 1.8599305968502813
  },
  {
    "date": "2026-01-23",
    "strategy": 3.436353569567117,
    "benchmark": 1.860605482423729
  },
  {
    "date": "2026-01-26",
    "strategy": 3.4604576936547624,
    "benchmark": 1.8700538804519953
  },
  {
    "date": "2026-01-27",
    "strategy": 3.5351248760475324,
    "benchmark": 1.8775046435455747
  },
  {
    "date": "2026-01-28",
    "strategy": 3.5842573334479693,
    "benchmark": 1.877315655812971
  },
  {
    "date": "2026-01-29",
    "strategy": 3.578745974676183,
    "benchmark": 1.8735902742661814
  },
  {
    "date": "2026-01-30",
    "strategy": 3.4855232986923794,
    "benchmark": 1.868002201945997
  },
  {
    "date": "2026-02-02",
    "strategy": 3.5143236963820796,
    "benchmark": 1.8772886340273154
  },
  {
    "date": "2026-02-03",
    "strategy": 3.6009019187495364,
    "benchmark": 1.8614154769254547
  },
  {
    "date": "2026-02-04",
    "strategy": 3.58646038442073,
    "benchmark": 1.852398933166721
  },
  {
    "date": "2026-02-05",
    "strategy": 3.4173090064325153,
    "benchmark": 1.829263835936899
  },
  {
    "date": "2026-02-06",
    "strategy": 3.5497986995688127,
    "benchmark": 1.8643578857561742
  },
  {
    "date": "2026-02-09",
    "strategy": 3.6287575273849537,
    "benchmark": 1.8733474077292522
  },
  {
    "date": "2026-02-10",
    "strategy": 3.6251467721549853,
    "benchmark": 1.8684071991968598
  },
  {
    "date": "2026-02-11",
    "strategy": 3.7039994502182374,
    "benchmark": 1.867975344927327
  },
  {
    "date": "2026-02-12",
    "strategy": 3.560615979867922,
    "benchmark": 1.8391172312160282
  },
  {
    "date": "2026-02-13",
    "strategy": 3.6629629419316325,
    "benchmark": 1.840412958791612
  },
  {
    "date": "2026-02-17",
    "strategy": 3.648433414934801,
    "benchmark": 1.8433823894079873
  },
  {
    "date": "2026-02-18",
    "strategy": 3.6957389696962646,
    "benchmark": 1.8526688214893057
  },
  {
    "date": "2026-02-19",
    "strategy": 3.716266727614083,
    "benchmark": 1.8477826565282245
  },
  {
    "date": "2026-02-20",
    "strategy": 3.7386085542040073,
    "benchmark": 1.8611454238358842
  },
  {
    "date": "2026-02-23",
    "strategy": 3.7072385403099526,
    "benchmark": 1.8421407054037144
  },
  {
    "date": "2026-02-24",
    "strategy": 3.774868159809468,
    "benchmark": 1.855530329730044
  },
  {
    "date": "2026-02-25",
    "strategy": 3.7610677413082834,
    "benchmark": 1.871187806847617
  },
  {
    "date": "2026-02-26",
    "strategy": 3.7620413767004677,
    "benchmark": 1.8607944701563326
  },
  {
    "date": "2026-02-27",
    "strategy": 3.765682554426459,
    "benchmark": 1.8518589917545658
  },
  {
    "date": "2026-03-02",
    "strategy": 3.8084894691972337,
    "benchmark": 1.8529118527932205
  },
  {
    "date": "2026-03-03",
    "strategy": 3.7198373236164666,
    "benchmark": 1.8365796548691857
  },
  {
    "date": "2026-03-04",
    "strategy": 3.7298368136860542,
    "benchmark": 1.8495374249259826
  },
  {
    "date": "2026-03-05",
    "strategy": 3.65748961731421,
    "benchmark": 1.8392251535916648
  },
  {
    "date": "2026-03-06",
    "strategy": 3.574010435929706,
    "benchmark": 1.8151182606801548
  },
  {
    "date": "2026-03-09",
    "strategy": 3.63546299130294,
    "benchmark": 1.8310186043346568
  },
  {
    "date": "2026-03-10",
    "strategy": 3.6337395984651524,
    "benchmark": 1.8280760307369517
  },
  {
    "date": "2026-03-11",
    "strategy": 3.6554650545800524,
    "benchmark": 1.8236218848123888
  }
]